parquet2csv/__init__.py
parquet2csv/cli.py
parquet2csv-0.8.dist-info/LICENSE
parquet2csv-0.8.dist-info/METADATA
parquet2csv-0.8.dist-info/WHEEL
parquet2csv-0.8.dist-info/entry_points.txt
parquet2csv-0.8.dist-info/top_level.txt
parquet2csv-0.8.dist-info/RECORD
